hashicorp_vault_client_api/__init__.py
hashicorp_vault_client_api/models/__init__.py
hashicorp_vault_client_api/models/auth.py
hashicorp_vault_client_api/models/secrets.py
hashicorp_vault_client_api/models/sys.py
hashicorp_vault_client_api/vault_client.py
hashicorp_vault_client_api/views/__init__.py
hashicorp_vault_client_api-0.5.1.dist-info/LICENSE.md
hashicorp_vault_client_api-0.5.1.dist-info/WHEEL
hashicorp_vault_client_api-0.5.1.dist-info/METADATA
hashicorp_vault_client_api-0.5.1.dist-info/RECORD
